MANIFEST.in
README.markdown
setup.py
pyblosxomdrafts/__init__.py
pyblosxomdrafts.egg-info/PKG-INFO
pyblosxomdrafts.egg-info/SOURCES.txt
pyblosxomdrafts.egg-info/dependency_links.txt
pyblosxomdrafts.egg-info/top_level.txt