Metadata-Version: 1.1
Name: pyblosxomdrafts
Version: 0.0.2
Summary: A Pyblosxom plugin that lets you save draft posts
Home-page: https://github.com/seanh/pyblosxomdrafts
Author: Sean Hammond
Author-email: pyblosxomdrafts@seanh.cc
License: GPLv3
Keywords: pyblosxom
Platform: UNKNOWN
Classifier: Development Status :: 3 - Alpha
Classifier: License :: OSI Approved :: GNU General Public License v3 (GPLv3)
Classifier: Programming Language :: Python :: 2.7
